framework/__init__.py
framework/allure/__init__.py
framework/allure/step.py
framework/config/__init__.py
framework/config/csv.py
framework/config/yaml.py
framework/io/__init__.py
framework/io/config.py
framework/mod/__init__.py
framework/mod/mod.py
framework/plugin/__init__.py
framework/plugin/functions.py
framework/plugin/mark.py
framework/plugin/extra/__init__.py
framework/plugin/extra/metadata_property.py
pytest_ch_framework-1.0.1.dist-info/METADATA
pytest_ch_framework-1.0.1.dist-info/WHEEL
pytest_ch_framework-1.0.1.dist-info/entry_points.txt
pytest_ch_framework-1.0.1.dist-info/top_level.txt
pytest_ch_framework-1.0.1.dist-info/RECORD
